gpxconverter/__init__.py
gpxconverter/__main__.py
gpxconverter/converter.py
gpxconverter-0.9.4.dist-info/DESCRIPTION.rst
gpxconverter-0.9.4.dist-info/METADATA
gpxconverter-0.9.4.dist-info/RECORD
gpxconverter-0.9.4.dist-info/WHEEL
gpxconverter-0.9.4.dist-info/entry_points.txt
gpxconverter-0.9.4.dist-info/metadata.json
gpxconverter-0.9.4.dist-info/top_level.txt
