Metadata-Version: 2.0
Name: gpxconverter
Version: 0.9.4
Summary: gpx to csv converter. it supports waypoint elements except extensions. Values in extensions will be ignored.
Home-page: https://github.com/linusyoung/GPXConverter
Author: Linus Yang
Author-email: linusyoungrice@gmail.com
License: MIT
Download-URL: https://github.com/linusyoung/GPXConverter/archive/0.9.4.tar.gz
Platform: UNKNOWN
Classifier: Natural Language :: English
Classifier: Operating System :: MacOS :: MacOS X
Classifier: Operating System :: POSIX
Classifier: Operating System :: POSIX :: BSD
Classifier: Operating System :: POSIX :: Linux
Classifier: Operating System :: Microsoft :: Windows
Classifier: Programming Language :: Python
Classifier: Programming Language :: Python :: 3
Classifier: Programming Language :: Python :: 3.2
Classifier: Programming Language :: Python :: 3.3
Classifier: Programming Language :: Python :: 3.4
Classifier: Programming Language :: Python :: 3.5
Classifier: Programming Language :: Python :: 3.6
Requires-Python: >=3
